paretl/__init__.py
paretl/etl.py
paretl/io.py
paretl/parameter.py
paretl/sweep.py
paretl/util.py
paretl-0.3.0.dist-info/AUTHORS.rst
paretl-0.3.0.dist-info/LICENSE
paretl-0.3.0.dist-info/METADATA
paretl-0.3.0.dist-info/WHEEL
paretl-0.3.0.dist-info/top_level.txt
paretl-0.3.0.dist-info/RECORD
